tapir/__init__.py
tapir/_version.py
tapir/auxiliary.py
tapir/edger.py
tapir/embedding.py
tapir/gsets.py
tapir/immune.py
tapir/plotting.py
tapir/stats.py
tapir_rna-0.1.0.dist-info/LICENSE
tapir_rna-0.1.0.dist-info/METADATA
tapir_rna-0.1.0.dist-info/WHEEL
tapir_rna-0.1.0.dist-info/top_level.txt
tapir_rna-0.1.0.dist-info/RECORD
