Metadata-Version: 2.1
Name: tapir-rna
Version: 0.1.0
Summary: Transcriptional Analysis in Python Imported from R
Home-page: https://github.com/fcomitani/tapir
Download-URL: https://github.com/fcomitani/tapir/archive/0.1.0.tar.gz
Author: Federico Comitani, Josh O. Nash
Author-email: federico.comitani@gmail.com
License: MIT
Keywords: clustering recursion dimension-reduction k-NN hiearchical-clustering optimal-clusters differential-evolution
Classifier: Development Status :: 4 - Beta
Classifier: Intended Audience :: Science/Research
Classifier: Topic :: Scientific/Engineering
Classifier: License :: OSI Approved :: MIT License
Classifier: Programming Language :: Python
Classifier: Programming Language :: Python :: 3.7
Classifier: Programming Language :: Python :: 3.8
License-File: LICENSE
Requires-Dist: numpy (>=1.20.2)
Requires-Dist: pandas (>=1.1.3)
Requires-Dist: gseapy (>=0.9.5)
Requires-Dist: lifelines (>=0.21.0)
Requires-Dist: rpy2 (>=3.4.5)
Requires-Dist: seaborn (>=0.11.1)
Requires-Dist: scikit-learn (>=0.4.6)
Requires-Dist: statsmodels (>=0.11.1)
Requires-Dist: umap-learn (>=0.3.9)
